{"_meta":{"disclaimer":"Statistical indicators derived from public data. Patterns may have legitimate explanations.","generated_note":"Temporal knowledge-graph analytics, computed offline and validated."},"link_prediction":{"_meta":{"method":"Rolling chronological split: for each cut year T, score every sizeable firm pair (>= P1B flood-control value) that shares an office but has no recorded joint venture by T, using a time-decayed Adamic-Adar over their shared offices (half-life 2 years). Positives are pairs whose FIRST joint venture appears in T+1. Skill is ROC-AUC. Two nulls: a label-permutation test and a degree-preserving configuration-model rewiring of the award graph.","disclaimer":"Statistical indicators derived from public data. Patterns may have legitimate explanations."},"macro_auc":0.702,"by_year":[{"train_upto":2018,"predict":2019,"candidates":6465,"new_jv":17,"auc":0.631,"auc_null_mean":0.478,"p_label_perm":0.024,"p_degree_null":0.0083,"top_hits":[{"firms":["ST. TIMOTHY CONSTRUCTION CORPORATION","ST. MATTHEW GEN. CONTRACTOR & DEVELOPMENT CORP"],"score":1.043},{"firms":["AKN CONSTRUCTION CORPORATION","AARCON BUILDERS"],"score":0.923},{"firms":["L.R. TIQUI BUILDERS, INC","PERSAN CONSTRUCTION, INC"],"score":0.752},{"firms":["SUPREME ABF CONST. & CONST. SUPPLY COMPANY INC","REDSON CONSTRUCTION AND SUPPLIES, INC"],"score":0.713},{"firms":["OMNICON BUILDERS","KLDS TRADING & CONSTRUCTION"],"score":0.662}]},{"train_upto":2019,"predict":2020,"candidates":8123,"new_jv":18,"auc":0.665,"auc_null_mean":0.401,"p_label_perm":0.004,"p_degree_null":0.0083,"top_hits":[{"firms":["RCDS CONSTRUCTION & SUPPLY, INC.(FOR RCDS CONST","3DIAMONDS CONSTRUCTION CORPORATION"],"score":0.781},{"firms":["R.A. MATIAS CONSTRUCTION AND DEVELOPERS INC","ARCINUE COMM'L CORPORATION"],"score":0.616},{"firms":["AKN CONSTRUCTION CORPORATION","E. F. CHUA CONSTRUCTION, INC"],"score":0.587},{"firms":["N.B. AVILA CONSTRUCTION","KLDS TRADING & CONSTRUCTION"],"score":0.579},{"firms":["EGB CONSTRUCTION CORPORATION","DRAGON TWELVE BUILDERS & CONSTRUCTION SUPPLY"],"score":0.558}]},{"train_upto":2020,"predict":2021,"candidates":9680,"new_jv":16,"auc":0.699,"auc_null_mean":0.397,"p_label_perm":0.006,"p_degree_null":0.0083,"top_hits":[{"firms":["FFJJ CONSTRUCTION","LEGACY CONSTRUCTION CORPORATION"],"score":2.644},{"firms":["JGO BUILDERS","B. VICENCIO BUILDERS (BVB), INC"],"score":0.525},{"firms":["BNR CONSTRUCTION & DEVELOPMENT CORP","VSP STRUCTURE VENTURES CORP"],"score":0.425},{"firms":["LCTING CONSTRUCTION AND DEVELOPMENT CORPORATION","A.T. DUMLAO CONSTRUCTION, INC. FORMERLYANDONI T. D"],"score":0.359},{"firms":["TCSC CORP","EFREN RAMIREZ CONSTRUCTION AND GENERAL SERVICES CORPORATION"],"score":0.346}]},{"train_upto":2021,"predict":2022,"candidates":11375,"new_jv":27,"auc":0.652,"auc_null_mean":0.43,"p_label_perm":0.008,"p_degree_null":0.0083,"top_hits":[{"firms":["FAIRCHILD BUILDERS & DEVELOPERS, INC","LANOY CONSTRUCTION"],"score":0.819},{"firms":["EZJONES CONSTRUCTION INC","JGO BUILDERS"],"score":0.721},{"firms":["ABU CONSTRUCTION","AGONG BUILDERS AND CONSTRUCTION SUPPLY, INC"],"score":0.629},{"firms":["LANAO BUILDER AND ENTERPRISES","KOUZBARY BUILDERS"],"score":0.616},{"firms":["NEWBIG FOUR J CONSTRUCTION INC","PRIME PACIFIC MARINE & INDUSTRIAL SERVICES CORP"],"score":0.586}]},{"train_upto":2022,"predict":2023,"candidates":13766,"new_jv":30,"auc":0.759,"auc_null_mean":0.441,"p_label_perm":0.002,"p_degree_null":0.0083,"top_hits":[{"firms":["PANAY EAST COAST CONSTRUCTION & SUPPLY","A.D. PENDON CONSTRUCTION & SUPPLY, INC"],"score":1.369},{"firms":["SUNWEST, INC","HI-TONE CONSTRUCTION & DEVELOPMENT CORP"],"score":1.083},{"firms":["EQUI-PARCO CONSTRUCTION COMPANY","ME 3 CONSTRUCTION"],"score":1.053},{"firms":["NEWBIG FOUR J CONSTRUCTION INC","JTC CRUZ CONSTRUCTION CO., INC"],"score":0.767},{"firms":["L.R. TIQUI BUILDERS, INC","M3 KONSTRACT CORPORATION"],"score":0.763}]},{"train_upto":2023,"predict":2024,"candidates":17750,"new_jv":23,"auc":0.761,"auc_null_mean":0.435,"p_label_perm":0.002,"p_degree_null":0.0083,"top_hits":[{"firms":["IM CONSTRUCTION CORPORATION","JAGONBUILD CONSTRUCTION CORP. (FOR. JAGON BUILDERS"],"score":0.886},{"firms":["LANAO BUILDER AND ENTERPRISES","AL HUSSEIN CONSTRUCTION"],"score":0.753},{"firms":["ALPHA & OMEGA GEN. CONTRACTOR & DEVELOPMENT CORP","A.C. RIVERO DEVELOPMENT CORPORATION"],"score":0.73},{"firms":["HHH DEVELOPER AND REAL ESTATE INC","RCDG CONSTRUCTION CORPORATION"],"score":0.584},{"firms":["ANORE CONSTRUCTION","ST. TIMOTHY CONSTRUCTION CORPORATION"],"score":0.544}]},{"train_upto":2024,"predict":2025,"candidates":20856,"new_jv":6,"auc":0.744,"auc_null_mean":0.5,"p_label_perm":0.024,"p_degree_null":0.0083,"top_hits":[{"firms":["J. SIMEON CONSTRUCTION","TOUGHBUILT CONSTRUCTION & TRADING, INC"],"score":0.775},{"firms":["ROCK-WBL CONSTRUCTION CORP. (FOR: ROCK-WBL CONSTRUCTION TRADING & SERVICES)","SILVERWOLVES CONSTRUCTION CORPORATION"],"score":0.579},{"firms":["ALPHA & OMEGA GEN. CONTRACTOR & DEVELOPMENT CORP","JCA CONSTRUCTION AND CONSTRUCTION SUPPLY"],"score":0.327},{"firms":["JAGONBUILD CONSTRUCTION CORP. (FOR. JAGON BUILDERS","PERSAN CONSTRUCTION, INC"],"score":0.311},{"firms":["MEGAPOLITAN BUILDERS AND CONSTRUCTION SUPPLY","ALPHA & OMEGA GEN. CONTRACTOR & DEVELOPMENT CORP"],"score":0.31}]}]},"dynamic_communities":{"_meta":{"method":"Louvain communities on the cumulative firm co-location graph each year (firms linked when they share >= 2 flood-control district offices, among firms with >= P1B). Stability is the adjusted Rand index between one year's partition and the previous year's, on the firms present in both: higher means the cluster structure is settling.","disclaimer":"Statistical indicators derived from public data. Patterns may have legitimate explanations."},"by_year":[{"year":2018,"firms_linked":263,"communities":8,"largest":59,"top_sizes":[59,51,45,40,33],"stability_vs_prev":null},{"year":2019,"firms_linked":288,"communities":8,"largest":61,"top_sizes":[61,57,47,44,38],"stability_vs_prev":0.813},{"year":2020,"firms_linked":314,"communities":9,"largest":86,"top_sizes":[86,80,49,36,30],"stability_vs_prev":0.707},{"year":2021,"firms_linked":342,"communities":7,"largest":94,"top_sizes":[94,87,57,38,31],"stability_vs_prev":0.934},{"year":2022,"firms_linked":369,"communities":7,"largest":111,"top_sizes":[111,100,66,41,28],"stability_vs_prev":0.839},{"year":2023,"firms_linked":395,"communities":7,"largest":121,"top_sizes":[121,104,70,42,33],"stability_vs_prev":0.893},{"year":2024,"firms_linked":411,"communities":6,"largest":155,"top_sizes":[155,117,71,42,22],"stability_vs_prev":0.762},{"year":2025,"firms_linked":413,"communities":5,"largest":158,"top_sizes":[158,121,73,42,19],"stability_vs_prev":0.946}]},"change_points":{"_meta":{"method":"Pettitt's non-parametric single change-point test on each yearly structural series. The change year is where the series most sharply shifts level; the p-value is the approximate significance.","disclaimer":"Statistical indicators derived from public data. Patterns may have legitimate explanations."},"metrics":{"fc_value":{"change_year":2021,"p_value":0.0864,"before_mean":90956571263.51,"after_mean":260121195221.02},"named_share_pct":{"change_year":2020,"p_value":0.0661,"before_mean":6.95,"after_mean":12.22},"entrant_share_pct":{"change_year":2020,"p_value":0.0661,"before_mean":28.14,"after_mean":4.63},"cr10_pct":{"change_year":2019,"p_value":0.0864,"before_mean":19.33,"after_mean":15.05},"concentrated_deos":{"change_year":2021,"p_value":0.4135,"before_mean":61.33,"after_mean":49.25},"jv_giant_component":{"change_year":2020,"p_value":0.0661,"before_mean":286.6,"after_mean":1071.2}}},"motifs":{"_meta":{"method":"For each firm pair holding a recorded joint venture, compare the JV's first year to the median year of their shared-office awards. 'JV before awards' means the partnership predates the bulk of the shared money; 'awards before JV' the reverse. Sequence only, never a claim of intent.","disclaimer":"Statistical indicators derived from public data. Patterns may have legitimate explanations."},"counts":{"jv_before_awards":263,"awards_before_jv":66,"concurrent":89},"examples":[{"firms":["SUNWEST, INC","HI-TONE CONSTRUCTION & DEVELOPMENT CORP"],"jv_year":2023,"awards_median_year":2022.0,"relation":"awards_before_jv","shared_awards":393},{"firms":["ST. TIMOTHY CONSTRUCTION CORPORATION","ST. MATTHEW GEN. CONTRACTOR & DEVELOPMENT CORP"],"jv_year":2019,"awards_median_year":2020.0,"relation":"jv_before_awards","shared_awards":392},{"firms":["HI-TONE CONSTRUCTION & DEVELOPMENT CORP","CENTERWAYS CONSTRUCTION AND DEVELOPMENT INC"],"jv_year":2018,"awards_median_year":2022.0,"relation":"jv_before_awards","shared_awards":298},{"firms":["QM BUILDERS","QUIRANTE CONSTRUCTION CORPORATION"],"jv_year":2016,"awards_median_year":2023.0,"relation":"jv_before_awards","shared_awards":283},{"firms":["STO. CRISTO CONSTRUCTION & TRADING INC. (FOR: STO. CRISTO CONSTRUCTION & TRADING)","NORTHERN BUILDERS"],"jv_year":2018,"awards_median_year":2019.0,"relation":"jv_before_awards","shared_awards":272},{"firms":["ALPHA & OMEGA GEN. CONTRACTOR & DEVELOPMENT CORP","ELITE GENERAL CONTRACTOR AND DEVELOPMENT CORP"],"jv_year":2022,"awards_median_year":2022.0,"relation":"concurrent","shared_awards":271},{"firms":["ST. TIMOTHY CONSTRUCTION CORPORATION","AMETHYST HORIZON BUILDERS AND GEN. CONTRACTOR AND DEVELOPMENT CORP"],"jv_year":2022,"awards_median_year":2021.0,"relation":"awards_before_jv","shared_awards":271},{"firms":["ST. TIMOTHY CONSTRUCTION CORPORATION","ELITE GENERAL CONTRACTOR AND DEVELOPMENT CORP"],"jv_year":2022,"awards_median_year":2021.0,"relation":"awards_before_jv","shared_awards":267},{"firms":["L.R. TIQUI BUILDERS, INC","M3 KONSTRACT CORPORATION"],"jv_year":2023,"awards_median_year":2022.0,"relation":"awards_before_jv","shared_awards":267},{"firms":["L.R. TIQUI BUILDERS, INC","729 CONSTRUCTION, INC"],"jv_year":2023,"awards_median_year":2022.0,"relation":"awards_before_jv","shared_awards":242},{"firms":["AKN CONSTRUCTION CORPORATION","E. F. CHUA CONSTRUCTION, INC"],"jv_year":2020,"awards_median_year":2020.0,"relation":"concurrent","shared_awards":234},{"firms":["QM BUILDERS","FIRST GRANDEUR BUILDERS INC"],"jv_year":2018,"awards_median_year":2023.0,"relation":"jv_before_awards","shared_awards":226}]},"hetero":{"_meta":{"purpose":"The money-and-power schema: Person, Firm, Office and Institution nodes joined by typed, dated edges (linked_to, revoked, charged, lookout, donated, ...). Populated ONLY from the sourced overlay. Bulk SALN wealth and SOCE campaign-finance joins are not yet machine-readable public data; this is the interface, filled with the real, source-linked records that exist, ready to scale.","node_types":["Person","Firm","ProcuringEntity","Institution"],"edge_types":["linked_to","awarded","co_awarded","revoked","charged","lookout","donated","frozen","cleared"],"disclaimer":"Statistical indicators derived from public data. Patterns may have legitimate explanations."},"node_counts":{"Person":8,"Firm":16,"Institution":0},"edge_count":44,"edges":[{"head":"Cezarah \"Sarah\" Discaya","head_type":"Person","relation":"linked_to","tail":"31762","tail_type":"Firm","date":"2025-09-03","sources":["pcab075_inq","amlc_gma"]},{"head":"Cezarah \"Sarah\" Discaya","head_type":"Person","relation":"linked_to","tail":"38958","tail_type":"Firm","date":"2025-09-03","sources":["pcab075_inq","amlc_gma"]},{"head":"Cezarah \"Sarah\" Discaya","head_type":"Person","relation":"linked_to","tail":"39196","tail_type":"Firm","date":"2025-09-03","sources":["pcab075_inq","amlc_gma"]},{"head":"Cezarah \"Sarah\" Discaya","head_type":"Person","relation":"linked_to","tail":"40908","tail_type":"Firm","date":"2025-09-03","sources":["pcab075_inq","amlc_gma"]},{"head":"Cezarah \"Sarah\" Discaya","head_type":"Person","relation":"linked_to","tail":"45914","tail_type":"Firm","date":"2025-09-03","sources":["pcab075_inq","amlc_gma"]},{"head":"Cezarah \"Sarah\" Discaya","head_type":"Person","relation":"linked_to","tail":"49129","tail_type":"Firm","date":"2025-09-03","sources":["pcab075_inq","amlc_gma"]},{"head":"Cezarah \"Sarah\" Discaya","head_type":"Person","relation":"linked_to","tail":"52351","tail_type":"Firm","date":"2025-09-03","sources":["pcab075_inq","amlc_gma"]},{"head":"Cezarah \"Sarah\" Discaya","head_type":"Person","relation":"linked_to","tail":"45002","tail_type":"Firm","date":"2025-09-03","sources":["pcab075_inq","amlc_gma"]},{"head":"Cezarah \"Sarah\" Discaya","head_type":"Person","relation":"linked_to","tail":"49128","tail_type":"Firm","date":"2025-09-03","sources":["pcab075_inq","amlc_gma"]},{"head":"Pacifico \"Curlee\" Discaya","head_type":"Person","relation":"linked_to","tail":"31762","tail_type":"Firm","date":"2025-09-03","sources":["pcab075_inq"]},{"head":"Pacifico \"Curlee\" Discaya","head_type":"Person","relation":"linked_to","tail":"38958","tail_type":"Firm","date":"2025-09-03","sources":["pcab075_inq"]},{"head":"Pacifico \"Curlee\" Discaya","head_type":"Person","relation":"linked_to","tail":"39196","tail_type":"Firm","date":"2025-09-03","sources":["pcab075_inq"]},{"head":"Elizaldy \"Zaldy\" Co","head_type":"Person","relation":"linked_to","tail":"15906","tail_type":"Firm","date":"2025-11-19","sources":["sunwest_gma_file","co_fugitive_gma"]},{"head":"Eumir and Pamela Villanueva","head_type":"Person","relation":"linked_to","tail":"34061","tail_type":"Firm","date":"2025-09-04","sources":["doj_ilbo_inq"]},{"head":"Lawrence R. Lubiano","head_type":"Person","relation":"linked_to","tail":"34105","tail_type":"Firm","date":"2025","sources":["centerways_rappler","escudero_cleared_rappler"]},{"head":"Alex H. Abelido","head_type":"Person","relation":"linked_to","tail":"22465","tail_type":"Firm","date":"2025-09-04","sources":["doj_ilbo_inq"]},{"head":"MG Samidan Construction (Samidan family)","head_type":"Person","relation":"linked_to","tail":"33234","tail_type":"Firm","date":"2025-08-26","sources":["senate_subpoena_philstar"]},{"head":"Mark Allan Arevalo","head_type":"Person","relation":"linked_to","tail":"46535","tail_type":"Firm","date":"2025-09-05","sources":["wawao_mt"]},{"head":"31762","head_type":"Firm","relation":"license_revoked","tail":"PCAB revoked the contractor license (Board Resolution 075) o","tail_type":"Institution","date":"2025-09","sources":["pcab075_inq"]},{"head":"31762","head_type":"Firm","relation":"sec_cancelled","tail":"SEC cancelled the corporate registration for false beneficia","tail_type":"Institution","date":"2025-11-26","sources":["sec_gma"]},{"head":"31762","head_type":"Firm","relation":"amlc_freeze","tail":"AMLC secured freeze orders on accounts tied to the Discaya f","tail_type":"Institution","date":"2025-09","sources":["amlc_gma"]},{"head":"38958","head_type":"Firm","relation":"license_revoked","tail":"PCAB revoked the contractor license (Board Resolution 075) o","tail_type":"Institution","date":"2025-09","sources":["pcab075_inq"]},{"head":"38958","head_type":"Firm","relation":"amlc_freeze","tail":"AMLC secured freeze orders on accounts tied to the Discaya f","tail_type":"Institution","date":"2025-09","sources":["amlc_gma"]},{"head":"39196","head_type":"Firm","relation":"license_revoked","tail":"PCAB revoked the contractor license (Board Resolution 075) o","tail_type":"Institution","date":"2025-09","sources":["pcab075_inq"]},{"head":"39196","head_type":"Firm","relation":"sec_cancelled","tail":"SEC cancelled the corporate registration for false beneficia","tail_type":"Institution","date":"2025-11-26","sources":["sec_gma"]},{"head":"40908","head_type":"Firm","relation":"license_revoked","tail":"PCAB revoked the contractor license (Board Resolution 075) o","tail_type":"Institution","date":"2025-09","sources":["pcab075_inq"]},{"head":"45914","head_type":"Firm","relation":"license_revoked","tail":"PCAB revoked the contractor license (Board Resolution 075) o","tail_type":"Institution","date":"2025-09","sources":["pcab075_inq"]},{"head":"49129","head_type":"Firm","relation":"license_revoked","tail":"PCAB revoked the contractor license (Board Resolution 075) o","tail_type":"Institution","date":"2025-09","sources":["pcab075_inq"]},{"head":"52351","head_type":"Firm","relation":"license_revoked","tail":"PCAB revoked the contractor license (Board Resolution 075) o","tail_type":"Institution","date":"2025-09","sources":["pcab075_inq"]},{"head":"45002","head_type":"Firm","relation":"license_revoked","tail":"PCAB revoked the contractor license (Board Resolution 075) o","tail_type":"Institution","date":"2025-09","sources":["pcab075_inq"]},{"head":"49128","head_type":"Firm","relation":"license_revoked","tail":"PCAB revoked the contractor license (Board Resolution 075) o","tail_type":"Institution","date":"2025-09","sources":["pcab075_inq"]},{"head":"15906","head_type":"Firm","relation":"charged_pending","tail":"The Ombudsman charged company directors and Zaldy Co before ","tail_type":"Institution","date":"2025-11","sources":["sunwest_gma_file"]},{"head":"15906","head_type":"Firm","relation":"under_investigation","tail":"Co is reported to have left the country; the Sandiganbayan a","tail_type":"Institution","date":"2026-06","sources":["co_fugitive_gma"]},{"head":"46535","head_type":"Firm","relation":"blacklisted","tail":"DPWH ordered perpetual disqualification for ghost flood-cont","tail_type":"Institution","date":"2025-09-05","sources":["wawao_mt"]},{"head":"48517","head_type":"Firm","relation":"blacklisted","tail":"DPWH ordered perpetual disqualification for ghost flood-cont","tail_type":"Institution","date":"2025-09-05","sources":["wawao_mt"]},{"head":"34061","head_type":"Firm","relation":"flagged_review","tail":"Flagged in a COA fraud audit over a riverbank protection pro","tail_type":"Institution","date":"2025-11","sources":["topnotch_wiki"]},{"head":"34061","head_type":"Firm","relation":"lookout_order","tail":"Owners named on the DOJ immigration lookout bulletin order (","tail_type":"Institution","date":"2025-09","sources":["doj_ilbo_inq"]},{"head":"34061","head_type":"Firm","relation":"under_investigation","tail":"Named in news tracking of Ombudsman and ICI referrals arisin","tail_type":"Institution","date":"2026","sources":["topnotch_cases_rappler"]},{"head":"34105","head_type":"Firm","relation":"political_tie","tail":"Reported as the top campaign donor of Senate President Chiz ","tail_type":"Institution","date":"2022","sources":["centerways_rappler"]},{"head":"34105","head_type":"Firm","relation":"cleared","tail":"The Comelec cleared both Escudero and Lubiano of election-fi","tail_type":"Institution","date":"2026","sources":["escudero_cleared_rappler"]},{"head":"22465","head_type":"Firm","relation":"lookout_order","tail":"The firm's president was named on the DOJ immigration lookou","tail_type":"Institution","date":"2025-09","sources":["doj_ilbo_inq"]},{"head":"22465","head_type":"Firm","relation":"performance_flag","tail":"President Marcos said initial findings suggested several of ","tail_type":"Institution","date":"2025","sources":["samidan_inq"]},{"head":"33234","head_type":"Firm","relation":"capitalization_flag","tail":"SEC records show about PHP 250,000 paid-up capital while the","tail_type":"Institution","date":"2025","sources":["samidan_inq"]},{"head":"33234","head_type":"Firm","relation":"under_investigation","tail":"Subpoenaed by the Senate Blue Ribbon Committee and submitted","tail_type":"Institution","date":"2025","sources":["senate_subpoena_philstar"]}]}}